Workbook
Name aporte: APP!$D$17:$D$17
Name patrimonio: APP!$D$20:$D$20
Name Perfil: APP!$C$31:$C$31
Name qtd_anos: APP!$D$18:$D$18
Name rendimento_carteira: APP!$D$13:$D$13
Name taxa_mensal: APP!$D$19:$D$19

Sheet APP
B11: Configurações
B12: Salário | D12: 7500
B13: Rendimento carteira | D13: 0.01
B14: Sugestão e Investimento (30%) | D14: =D12*30% -> 2250
B16: Investimento mensal
B17: Quanto investir por mês? | D17: 2250
B18: Por quantos anos? | D18: 5
B19: Taxa de rendimento mensal? | D19: 0.01079
B20: Patrimônio acumulado? | D20: =FV(D19,D18*12,D17*-1) -> 188498.06
B21: Dividendos mensais? | D21: =D20*1% -> 1884.9806
B23: Cenários | D23: Dividendo
A24: 2 | B24: Quanto em 2 anos? | C24: =FV($D$19,$A24*12,$D$17*-1) -> 61262.161 | D24: =C24*$D$13 -> 612.62161
A25: 5 | B25: Quanto em 5 anos? | C25: =FV($D$19,$A25*12,$D$17*-1) -> 188498.06 | D25: =C25*$D$13 -> 1884.9806
A26: 10 | B26: Quanto em 10 anos? | C26: =FV($D$19,$A26*12,$D$17*-1) -> 547389.48 | D26: =C26*$D$13 -> 5473.8948
A27: 20 | B27: Quanto em 20 anos? | C27: =FV($D$19,$A27*12,$D$17*-1) -> 2531696.4 | D27: =C27*$D$13 -> 25316.964
A28: 30 | B28: Quanto em 30 anos? | C28: =FV($D$19,$A28*12,$D$17*-1) -> 9724881.7 | D28: =C28*$D$13 -> 97248.817
B31: Perfil | C31: Conservador
B32: Valor a ser investido por mês | C32: {=aporte} -> 2250
B34: Tipo de FII | C34: Percentual sugerido | D34: Valores
B35: Papel | C35: {=VLOOKUP(Perfil&"-"&B35,Planilha2!$A$2:$D$20,4,FALSE)} -> 0.3 | D35: =C35*$C$32 -> 675
B36: Tijolo | C36: {=VLOOKUP(Perfil&"-"&B36,Planilha2!$A$2:$D$20,4,FALSE)} -> 0.5 | D36: =C36*$C$32 -> 1125
B37: Híbridos | C37: {=VLOOKUP(Perfil&"-"&B37,Planilha2!$A$2:$D$20,4,FALSE)} -> 0.1 | D37: =C37*$C$32 -> 225
B38: FOFs | C38: {=VLOOKUP(Perfil&"-"&B38,Planilha2!$A$2:$D$20,4,FALSE)} -> 0.1 | D38: =C38*$C$32 -> 225
B39: Desenvolvimento | C39: {=VLOOKUP(Perfil&"-"&B39,Planilha2!$A$2:$D$20,4,FALSE)} -> 0 | D39: =C39*$C$32 -> 0
B40: Hotelarias | C40: {=VLOOKUP(Perfil&"-"&B40,Planilha2!$A$2:$D$20,4,FALSE)} -> 0 | D40: =C40*$C$32 -> 0
D41: =SUM(D35:D40) -> 2250

Sheet Planilha2
A2: Chave | B2: Perfil | C2: Tipo de FII | D2: %
A3: =B3&"-"&C3 -> Conservador-Papel | B3: Conservador | C3: Papel | D3: 0.3 | H3: %
A4: =B4&"-"&C4 -> Conservador-Tijolo | B4: Conservador | C4: Tijolo | D4: 0.5 | G4: Moderado-Tijolo | H4: =VLOOKUP(G4,A2:D20,4,FALSE) -> 0.35
A5: =B5&"-"&C5 -> Conservador-Híbridos | B5: Conservador | C5: Híbridos | D5: 0.1
A6: =B6&"-"&C6 -> Conservador-FOFs | B6: Conservador | C6: FOFs | D6: 0.1
A7: =B7&"-"&C7 -> Conservador-Desenvolvimento | B7: Conservador | C7: Desenvolvimento | D7: 0
A8: =B8&"-"&C8 -> Conservador-Hotelarias | B8: Conservador | C8: Hotelarias | D8: 0
A9: =B9&"-"&C9 -> Moderado-Papel | B9: Moderado | C9: Papel | D9: 0.32
A10: =B10&"-"&C10 -> Moderado-Tijolo | B10: Moderado | C10: Tijolo | D10: 0.35
A11: =B11&"-"&C11 -> Moderado-Híbridos | B11: Moderado | C11: Híbridos | D11: 0.08
A12: =B12&"-"&C12 -> Moderado-FOFs | B12: Moderado | C12: FOFs | D12: 0.05
A13: =B13&"-"&C13 -> Moderado-Desenvolvimento | B13: Moderado | C13: Desenvolvimento | D13: 0.1
A14: =B14&"-"&C14 -> Moderado-Hotelarias | B14: Moderado | C14: Hotelarias | D14: 0.1
A15: =B15&"-"&C15 -> Agressivo-Papel | B15: Agressivo | C15: Papel | D15: 0.5
A16: =B16&"-"&C16 -> Agressivo-Tijolo | B16: Agressivo | C16: Tijolo | D16: 0.1
... A20: =B20&"-"&C20 -> Agressivo-Hotelarias | B20: Agressivo | C20: Hotelarias | D20: 0.1
